LICENSE
README.md
setup.py
hyperdyn/__init__.py
hyperdyn/cli.py
hyperdyn/data_handling.py
hyperdyn/utils.py
hyperdyn.egg-info/PKG-INFO
hyperdyn.egg-info/SOURCES.txt
hyperdyn.egg-info/dependency_links.txt
hyperdyn.egg-info/entry_points.txt
hyperdyn.egg-info/requires.txt
hyperdyn.egg-info/top_level.txt
tests/__init__.py
tests/test_cli.py
tests/test_data_handling.py
tests/test_utils.py