Metadata-Version: 2.1
Name: hyperdyn
Version: 0.1.0
Summary: A collection of powerful tools from Hyperdyn.
Home-page: https://github.com/hyperdyn.ai/hyperdyn
Author: Skandan V
Author-email: skandanskandu23456@gmail.com
Classifier: Programming Language :: Python :: 3
Classifier: License :: OSI Approved :: MIT License
Classifier: Operating System :: OS Independent
Requires-Python: >=3.7
License-File: LICENSE
Requires-Dist: pandas
Requires-Dist: numpy
